{"cameraMode":{"drawMode":0,"name":"Shaded","section":"Shading Mode"},"sceneLighting":true,"audioPlay":false,"sceneViewState":{"showFog":true,"showMaterialUpdate":false,"showSkybox":true,"showFlares":true,"showImageEffects":true,"showParticleSystems":true},"in2DMode":false,"pivot":{"x":-83.81248474121094,"y":-76.8819580078125,"z":-116.11954498291016},"rotation":{"x":0.19118322432041169,"y":-0.8021559119224548,"z":0.3382056653499603,"w":0.45344439148902895},"size":344.5146789550781,"orthographic":false}